invokescons/__init__.py
invokescons/__main__.py
invokescons/command_line.py
invokescons-1.7.dist-info/LICENSE
invokescons-1.7.dist-info/METADATA
invokescons-1.7.dist-info/WHEEL
invokescons-1.7.dist-info/entry_points.txt
invokescons-1.7.dist-info/top_level.txt
invokescons-1.7.dist-info/zip-safe
invokescons-1.7.dist-info/RECORD
