Metadata-Version: 2.1
Name: invokescons
Version: 1.7
Summary: SCons - a software construction tool
Home-page: https://github.com/PierceLBrooks/invokescons
Author: Pierce L. Brooks
Author-email: piercebrks@gmail.com
Maintainer: Pierce L. Brooks
Maintainer-email: piercebrks@gmail.com
License: MIT
Platform: UNKNOWN
Classifier: Environment :: Console
Classifier: License :: OSI Approved :: MIT License
Classifier: Intended Audience :: Developers
Classifier: Topic :: Software Development
License-File: LICENSE
Requires-Dist: scons
